{"Air Response Unit": {"# OH": 0, "OH WR": null, "# GD": 0, "GD WR": null, "# GIH": 0, "GIH WR": null, "IWD": null, "ALSA": 5.186737804878049, "name": "Air Response Unit", "color": "W", "rarity": "uncommon"}, "Alacrian Armory": {"# OH": 0, "OH WR": null, "# GD": 0, "GD WR": null, "# GIH": 0, "GIH WR": null, "IWD": null, "ALSA": 5.812921183709347, "name": "Alacrian Armory", "color": "W", "rarity": "uncommon"}, "Basri, Tomorrow's Champion": {"# OH": 0, "OH WR": null, "# GD": 0, "GD WR": null, "# GIH": 0, "GIH WR": null, "IWD": null, "ALSA": 2.332260659694288, "name": "Basri, Tomorrow's Champion", "color": "W", "rarity": "rare"}, "Brightfield Glider": {"# OH": 0, "OH WR": null, "# GD": 0, "GD WR": null, "# GIH": 0, "GIH WR": null, "IWD": null, "ALSA": 7.040786095200474, "name": "Brightfield Glider", "color": "W", "rarity": "common"}, "Brightfield Mustang": {"# OH": 0, "OH WR": null, "# GD": 1, "GD WR": null, "# GIH": 1, "GIH WR": null, "IWD": null, "ALSA": 6.950120433560819, "name": "Brightfield Mustang", "color": "W", "rarity": "common"}, "Broadcast Rambler": {"# OH": 4, "OH WR": null, "# GD": 12, "GD WR": null, "# GIH": 16, "GIH WR": null, "IWD": null, "ALSA": 6.344585164125097, "name": "Broadcast Rambler", "color": "W", "rarity": "common"}, "Bulwark Ox": {"# OH": 0, "OH WR": null, "# GD": 0, "GD WR": null, "# GIH": 0, "GIH WR": null, "IWD": null, "ALSA": 2.0609442060085836, "name": "Bulwark Ox", "color": "W", "rarity": "rare"}, "Canyon Vaulter": {"# OH": 0, "OH WR": null, "# GD": 0, "GD WR": null, "# GIH": 0, "GIH WR": null, "IWD": null, "ALSA": 3.797782874617737, "name": "Canyon Vaulter", "color": "W", "rarity": "uncommon"}, "Cloudspire Captain": {"# OH": 0, "OH WR": null, "# GD": 0, "GD WR": null, "# GIH": 0, "GIH WR": null, "IWD": null, "ALSA": 3.6267087276551, "name": "Cloudspire Captain", "color": "W", "rarity": "uncommon"}, "Collision Course": {"# OH": 5, "OH WR": null, "# GD": 11, "GD WR": null, "# GIH": 16, "GIH WR": null, "IWD": null, "ALSA": 5.2757837081925185, "name": "Collision Course", "color": "W", "rarity": "common"}, "Daring Mechanic": {"# OH": 0, "OH WR": null, "# GD": 0, "GD WR": null, "# GIH": 0, "GIH WR": null, "IWD": null, "ALSA": 6.731604800729225, "name": "Daring Mechanic", "color": "W", "rarity": "common"}, "Detention Chariot": {"# OH": 0, "OH WR": null, "# GD": 0, "GD WR": null, "# GIH": 0, "GIH WR": null, "IWD": null, "ALSA": 3.475336322869955, "name": "Detention Chariot", "color": "W", "rarity": "uncommon"}, "Gallant Strike": {"# OH": 19, "OH WR": null, "# GD": 22, "GD WR": null, "# GIH": 41, "GIH WR": null, "IWD": null, "ALSA": 3.6729383506805444, "name": "Gallant Strike", "color": "W", "rarity": "uncommon"}, "Gloryheath Lynx": {"# OH": 1, "OH WR": null, "# GD": 0, "GD WR": null, "# GIH": 1, "GIH WR": null, "IWD": null, "ALSA": 2.8505986465382613, "name": "Gloryheath Lynx", "color": "W", "rarity": "uncommon"}, "Guardian Sunmare": {"# OH": 0, "OH WR": null, "# GD": 0, "GD WR": null, "# GIH": 0, "GIH WR": null, "IWD": null, "ALSA": 1.8838912133891212, "name": "Guardian Sunmare", "color": "W", "rarity": "rare"}, "Guidelight Synergist": {"# OH": 2, "OH WR": null, "# GD": 3, "GD WR": null, "# GIH": 5, "GIH WR": null, "IWD": null, "ALSA": 4.577866022099448, "name": "Guidelight Synergist", "color": "W", "rarity": "uncommon"}, "Interface Ace": {"# OH": 0, "OH WR": null, "# GD": 0, "GD WR": null, "# GIH": 0, "GIH WR": null, "IWD": null, "ALSA": 6.598981077147016, "name": "Interface Ace", "color": "W", "rarity": "common"}, "Leonin Surveyor": {"# OH": 0, "OH WR": null, "# GD": 0, "GD WR": null, "# GIH": 0, "GIH WR": null, "IWD": null, "ALSA": 5.499171759867481, "name": "Leonin Surveyor", "color": "W", "rarity": "common"}, "Lightshield Parry": {"# OH": 0, "OH WR": null, "# GD": 0, "GD WR": null, "# GIH": 0, "GIH WR": null, "IWD": null, "ALSA": 7.67356950799566, "name": "Lightshield Parry", "color": "W", "rarity": "common"}, "Lightwheel Enhancements": {"# OH": 0, "OH WR": null, "# GD": 0, "GD WR": null, "# GIH": 0, "GIH WR": null, "IWD": null, "ALSA": 7.699431514503669, "name": "Lightwheel Enhancements", "color": "W", "rarity": "common"}, "Lotusguard Disciple": {"# OH": 2, "OH WR": null, "# GD": 3, "GD WR": null, "# GIH": 5, "GIH WR": null, "IWD": null, "ALSA": 6.218389604967907, "name": "Lotusguard Disciple", "color": "W", "rarity": "common"}, "Nesting Bot": {"# OH": 0, "OH WR": null, "# GD": 0, "GD WR": null, "# GIH": 0, "GIH WR": null, "IWD": null, "ALSA": 4.238283261802575, "name": "Nesting Bot", "color": "W", "rarity": "uncommon"}, "Perilous Snare": {"# OH": 37, "OH WR": null, "# GD": 50, "GD WR": null, "# GIH": 87, "GIH WR": null, "IWD": null, "ALSA": 1.5947187141216992, "name": "Perilous Snare", "color": "W", "rarity": "rare"}, "Pride of the Road": {"# OH": 0, "OH WR": null, "# GD": 0, "GD WR": null, "# GIH": 0, "GIH WR": null, "IWD": null, "ALSA": 4.3492422922835745, "name": "Pride of the Road", "color": "W", "rarity": "uncommon"}, "Ride's End": {"# OH": 54, "OH WR": null, "# GD": 83, "GD WR": null, "# GIH": 137, "GIH WR": null, "IWD": null, "ALSA": 4.036842871705257, "name": "Ride's End", "color": "W", "rarity": "common"}, "Roadside Assistance": {"# OH": 0, "OH WR": null, "# GD": 0, "GD WR": null, "# GIH": 0, "GIH WR": null, "IWD": null, "ALSA": 5.337197206122752, "name": "Roadside Assistance", "color": "W", "rarity": "uncommon"}, "Salvation Engine": {"# OH": 3, "OH WR": null, "# GD": 4, "GD WR": null, "# GIH": 7, "GIH WR": null, "IWD": null, "ALSA": null, "name": "Salvation Engine", "color": "W", "rarity": "mythic"}, "Skyseer's Chariot": {"# OH": 0, "OH WR": null, "# GD": 0, "GD WR": null, "# GIH": 0, "GIH WR": null, "IWD": null, "ALSA": 3.0301974448315914, "name": "Skyseer's Chariot", "color": "W", "rarity": "rare"}, "Spectacular Pileup": {"# OH": 6, "OH WR": null, "# GD": 8, "GD WR": null, "# GIH": 14, "GIH WR": null, "IWD": null, "ALSA": 2.3443548387096773, "name": "Spectacular Pileup", "color": "W", "rarity": "rare"}, "Spotcycle Scouter": {"# OH": 0, "OH WR": null, "# GD": 0, "GD WR": null, "# GIH": 0, "GIH WR": null, "IWD": null, "ALSA": 7.143419821771454, "name": "Spotcycle Scouter", "color": "W", "rarity": "common"}, "Sundial, Dawn Tyrant": {"# OH": 0, "OH WR": null, "# GD": 0, "GD WR": null, "# GIH": 0, "GIH WR": null, "IWD": null, "ALSA": 4.0421532846715325, "name": "Sundial, Dawn Tyrant", "color": "W", "rarity": "uncommon"}, "Swiftwing Assailant": {"# OH": 0, "OH WR": null, "# GD": 0, "GD WR": null, "# GIH": 0, "GIH WR": null, "IWD": null, "ALSA": 6.991277629101001, "name": "Swiftwing Assailant", "color": "W", "rarity": "common"}, "Tune Up": {"# OH": 1, "OH WR": null, "# GD": 0, "GD WR": null, "# GIH": 1, "GIH WR": null, "IWD": null, "ALSA": 5.853745704467354, "name": "Tune Up", "color": "W", "rarity": "uncommon"}, "Unswerving Sloth": {"# OH": 0, "OH WR": null, "# GD": 0, "GD WR": null, "# GIH": 0, "GIH WR": null, "IWD": null, "ALSA": 4.523553862140631, "name": "Unswerving Sloth", "color": "W", "rarity": "uncommon"}, "Valor's Flagship": {"# OH": 1, "OH WR": null, "# GD": 0, "GD WR": null, "# GIH": 1, "GIH WR": null, "IWD": null, "ALSA": null, "name": "Valor's Flagship", "color": "W", "rarity": "mythic"}, "Voyager Glidecar": {"# OH": 2, "OH WR": null, "# GD": 2, "GD WR": null, "# GIH": 4, "GIH WR": null, "IWD": null, "ALSA": 2.3731800766283526, "name": "Voyager Glidecar", "color": "W", "rarity": "rare"}, "Voyager Quickwelder": {"# OH": 0, "OH WR": null, "# GD": 0, "GD WR": null, "# GIH": 0, "GIH WR": null, "IWD": null, "ALSA": 6.098682778140649, "name": "Voyager Quickwelder", "color": "W", "rarity": "common"}, "Aether Syphon": {"# OH": 282, "OH WR": null, "# GD": 417, "GD WR": null, "# GIH": 699, "GIH WR": 0.5436337625178826, "IWD": -0.01127953227980516, "ALSA": 5.052132701421801, "name": "Aether Syphon", "color": "U", "rarity": "uncommon"}, "Bounce Off": {"# OH": 923, "OH WR": 0.5980498374864572, "# GD": 1496, "GD WR": 0.6450534759358288, "# GIH": 2419, "GIH WR": 0.6271186440677966, "IWD": 0.022554717840850724, "ALSA": 6.100494841019162, "name": "Bounce Off", "color": "U", "rarity": "common"}, "Caelorna, Coral Tyrant": {"# OH": 86, "OH WR": null, "# GD": 139, "GD WR": null, "# GIH": 225, "GIH WR": null, "IWD": null, "ALSA": 6.6459114778694675, "name": "Caelorna, Coral Tyrant", "color": "U", "rarity": "uncommon"}, "Diversion Unit": {"# OH": 359, "OH WR": null, "# GD": 524, "GD WR": 0.5801526717557252, "# GIH": 883, "GIH WR": 0.6002265005662514, "IWD": -0.0003270049688040011, "ALSA": 3.4391501650165015, "name": "Diversion Unit", "color": "U", "rarity": "uncommon"}, "Flood the Engine": {"# OH": 1333, "OH WR": 0.5933983495873969, "# GD": 2062, "GD WR": 0.628031037827352, "# GIH": 3395, "GIH WR": 0.6144329896907217, "IWD": 0.015453150001627725, "ALSA": 4.374655091190524, "name": "Flood the Engine", "color": "U", "rarity": "common"}, "Gearseeker Serpent": {"# OH": 62, "OH WR": null, "# GD": 114, "GD WR": null, "# GIH": 176, "GIH WR": null, "IWD": null, "ALSA": 6.267716120880278, "name": "Gearseeker Serpent", "color": "U", "rarity": "common"}, "Glitch Ghost Surveyor": {"# OH": 193, "OH WR": null, "# GD": 233, "GD WR": null, "# GIH": 426, "GIH WR": null, "IWD": null, "ALSA": 7.048512608353034, "name": "Glitch Ghost Surveyor", "color": "U", "rarity": "common"}, "Guidelight Optimizer": {"# OH": 357, "OH WR": null, "# GD": 530, "GD WR": 0.5830188679245283, "# GIH": 887, "GIH WR": 0.5918827508455468, "IWD": 0.008837768146584768, "ALSA": 5.889393447940318, "name": "Guidelight Optimizer", "color": "U", "rarity": "common"}, "Howler's Heavy": {"# OH": 611, "OH WR": 0.6153846153846154, "# GD": 1025, "GD WR": 0.6165853658536585, "# GIH": 1636, "GIH WR": 0.6161369193154034, "IWD": 0.027351872586431458, "ALSA": 6.608282147810581, "name": "Howler's Heavy", "color": "U", "rarity": "common"}, "Hulldrifter": {"# OH": 594, "OH WR": 0.5471380471380471, "# GD": 916, "GD WR": 0.6179039301310044, "# GIH": 1510, "GIH WR": 0.590066225165563, "IWD": 0.004485597757747817, "ALSA": 5.5800921045330965, "name": "Hulldrifter", "color": "U", "rarity": "common"}, "Keen Buccaneer": {"# OH": 1340, "OH WR": 0.5813432835820895, "# GD": 1959, "GD WR": 0.6191934660541092, "# GIH": 3299, "GIH WR": 0.603819339193695, "IWD": -0.012859519621228221, "ALSA": 5.582785772468097, "name": "Keen Buccaneer", "color": "U", "rarity": "common"}, "Memory Guardian": {"# OH": 78, "OH WR": null, "# GD": 105, "GD WR": null, "# GIH": 183, "GIH WR": null, "IWD": null, "ALSA": 3.7264038231780168, "name": "Memory Guardian", "color": "U", "rarity": "uncommon"}, "Midnight Mangler": {"# OH": 311, "OH WR": null, "# GD": 447, "GD WR": null, "# GIH": 758, "GIH WR": 0.5699208443271768, "IWD": 0.0008151532702662667, "ALSA": 6.05189421765138, "name": "Midnight Mangler", "color": "U", "rarity": "common"}, "Mindspring Merfolk": {"# OH": 235, "OH WR": null, "# GD": 376, "GD WR": null, "# GIH": 611, "GIH WR": 0.6890343698854338, "IWD": 0.12441705495444255, "ALSA": 2.6833898305084745, "name": "Mindspring Merfolk", "color": "U", "rarity": "rare"}, "Mu Yanling, Wind Rider": {"# OH": 89, "OH WR": null, "# GD": 146, "GD WR": null, "# GIH": 235, "GIH WR": null, "IWD": null, "ALSA": null, "name": "Mu Yanling, Wind Rider", "color": "U", "rarity": "mythic"}, "Nimble Thopterist": {"# OH": 675, "OH WR": 0.5718518518518518, "# GD": 1130, "GD WR": 0.5876106194690266, "# GIH": 1805, "GIH WR": 0.5817174515235457, "IWD": -0.017467331085149973, "ALSA": 5.547349939646659, "name": "Nimble Thopterist", "color": "U", "rarity": "common"}, "Possession Engine": {"# OH": 222, "OH WR": null, "# GD": 349, "GD WR": null, "# GIH": 571, "GIH WR": 0.670753064798599, "IWD": 0.06440385844939267, "ALSA": 1.861889927310488, "name": "Possession Engine", "color": "U", "rarity": "rare"}, "Rangers' Refueler": {"# OH": 721, "OH WR": 0.6227461858529819, "# GD": 1069, "GD WR": 0.6594948550046773, "# GIH": 1790, "GIH WR": 0.6446927374301676, "IWD": 0.031388016400124674, "ALSA": 3.113870077752696, "name": "Rangers' Refueler", "color": "U", "rarity": "uncommon"}, "Repurposing Bay": {"# OH": 0, "OH WR": null, "# GD": 1, "GD WR": null, "# GIH": 1, "GIH WR": null, "IWD": null, "ALSA": 5.296426292278238, "name": "Repurposing Bay", "color": "U", "rarity": "rare"}, "Riverchurn Monument": {"# OH": 203, "OH WR": null, "# GD": 303, "GD WR": null, "# GIH": 506, "GIH WR": 0.6383399209486166, "IWD": 0.1092592455264777, "ALSA": 3.492853361566967, "name": "Riverchurn Monument", "color": "U", "rarity": "rare"}, "Roadside Blowout": {"# OH": 613, "OH WR": 0.600326264274062, "# GD": 872, "GD WR": 0.6307339449541285, "# GIH": 1485, "GIH WR": 0.6181818181818182, "IWD": 0.0051948051948051965, "ALSA": 4.102116402116402, "name": "Roadside Blowout", "color": "U", "rarity": "uncommon"}, "Sabotage Strategist": {"# OH": 346, "OH WR": null, "# GD": 532, "GD WR": 0.631578947368421, "# GIH": 878, "GIH WR": 0.6093394077448747, "IWD": 0.02804570145116847, "ALSA": 3.6085141903171953, "name": "Sabotage Strategist", "color": "U", "rarity": "uncommon"}, "Scrounging Skyray": {"# OH": 119, "OH WR": null, "# GD": 212, "GD WR": null, "# GIH": 331, "GIH WR": null, "IWD": null, "ALSA": 3.92611821086262, "name": "Scrounging Skyray", "color": "U", "rarity": "uncommon"}, "Skystreak Engineer": {"# OH": 1292, "OH WR": 0.6238390092879257, "# GD": 1995, "GD WR": 0.6045112781954888, "# GIH": 3287, "GIH WR": 0.6121083054456952, "IWD": 0.010372529167970934, "ALSA": 5.367787772875723, "name": "Skystreak Engineer", "color": "U", "rarity": "common"}, "Slick Imitator": {"# OH": 172, "OH WR": null, "# GD": 215, "GD WR": null, "# GIH": 387, "GIH WR": null, "IWD": null, "ALSA": 5.4743661186960155, "name": "Slick Imitator", "color": "U", "rarity": "uncommon"}, "Spectral Interference": {"# OH": 865, "OH WR": 0.6335260115606937, "# GD": 1342, "GD WR": 0.6147540983606558, "# GIH": 2207, "GIH WR": 0.6221114635251472, "IWD": 0.01699782716151088, "ALSA": 6.300015650268663, "name": "Spectral Interference", "color": "U", "rarity": "common"}, "Spell Pierce": {"# OH": 13, "OH WR": null, "# GD": 28, "GD WR": null, "# GIH": 41, "GIH WR": null, "IWD": null, "ALSA": 7.410014005602241, "name": "Spell Pierce", "color": "U", "rarity": "uncommon"}, "Spikeshell Harrier": {"# OH": 620, "OH WR": 0.6403225806451613, "# GD": 854, "GD WR": 0.667447306791569, "# GIH": 1474, "GIH WR": 0.6560379918588873, "IWD": 0.05705609140639867, "ALSA": 2.8771709035992954, "name": "Spikeshell Harrier", "color": "U", "rarity": "uncommon"}, "Stall Out": {"# OH": 50, "OH WR": null, "# GD": 78, "GD WR": null, "# GIH": 128, "GIH WR": null, "IWD": null, "ALSA": 7.21651097960581, "name": "Stall Out", "color": "U", "rarity": "common"}, "Stock Up": {"# OH": 661, "OH WR": 0.642965204236006, "# GD": 1037, "GD WR": 0.6181292189006751, "# GIH": 1698, "GIH WR": 0.6277974087161367, "IWD": 0.01735378579561908, "ALSA": 4.208536585365854, "name": "Stock Up", "color": "U", "rarity": "uncommon"}, "Thopter Fabricator": {"# OH": 164, "OH WR": null, "# GD": 252, "GD WR": null, "# GIH": 416, "GIH WR": null, "IWD": null, "ALSA": 1.9397828232971372, "name": "Thopter Fabricator", "color": "U", "rarity": "rare"}, "Trade the Helm": {"# OH": 99, "OH WR": null, "# GD": 124, "GD WR": null, "# GIH": 223, "GIH WR": null, "IWD": null, "ALSA": 5.67322724734785, "name": "Trade the Helm", "color": "U", "rarity": "uncommon"}, "Transit Mage": {"# OH": 367, "OH WR": null, "# GD": 578, "GD WR": 0.6332179930795848, "# GIH": 945, "GIH WR": 0.6169312169312169, "IWD": 0.009856647141541885, "ALSA": 3.6981803797468356, "name": "Transit Mage", "color": "U", "rarity": "uncommon"}, "Trip Up": {"# OH": 849, "OH WR": 0.5736160188457008, "# GD": 1232, "GD WR": 0.6298701298701299, "# GIH": 2081, "GIH WR": 0.6069197501201345, "IWD": -0.0045667363663519644, "ALSA": 6.4462591935074816, "name": "Trip Up", "color": "U", "rarity": "common"}, "Unstoppable Plan": {"# OH": 0, "OH WR": null, "# GD": 0, "GD WR": null, "# GIH": 0, "GIH WR": null, "IWD": null, "ALSA": 5.482444733420026, "name": "Unstoppable Plan", "color": "U", "rarity": "rare"}, "Vnwxt, Verbose Host": {"# OH": 68, "OH WR": null, "# GD": 97, "GD WR": null, "# GIH": 165, "GIH WR": null, "IWD": null, "ALSA": 2.8282290279627165, "name": "Vnwxt, Verbose Host", "color": "U", "rarity": "rare"}, "Waxen Shapethief": {"# OH": 78, "OH WR": null, "# GD": 103, "GD WR": null, "# GIH": 181, "GIH WR": null, "IWD": null, "ALSA": 2.6970082749840865, "name": "Waxen Shapethief", "color": "U", "rarity": "rare"}, "Ancient Vendetta": {"# OH": 0, "OH WR": null, "# GD": 0, "GD WR": null, "# GIH": 0, "GIH WR": null, "IWD": null, "ALSA": 8.638067694944302, "name": "Ancient Vendetta", "color": "B", "rarity": "uncommon"}, "Back on Track": {"# OH": 26, "OH WR": null, "# GD": 37, "GD WR": null, "# GIH": 63, "GIH WR": null, "IWD": null, "ALSA": 4.2443724420191, "name": "Back on Track", "color": "B", "rarity": "uncommon"}, "Bloodghast": {"# OH": 0, "OH WR": null, "# GD": 0, "GD WR": null, "# GIH": 0, "GIH WR": null, "IWD": null, "ALSA": 3.705542168674699, "name": "Bloodghast", "color": "B", "rarity": "rare"}, "Carrion Cruiser": {"# OH": 7, "OH WR": null, "# GD": 12, "GD WR": null, "# GIH": 19, "GIH WR": null, "IWD": null, "ALSA": 3.7573670110983546, "name": "Carrion Cruiser", "color": "B", "rarity": "uncommon"}, "Chitin Gravestalker": {"# OH": 4, "OH WR": null, "# GD": 4, "GD WR": null, "# GIH": 8, "GIH WR": null, "IWD": null, "ALSA": 6.1882701606613635, "name": "Chitin Gravestalker", "color": "B", "rarity": "common"}, "Cryptcaller Chariot": {"# OH": 1, "OH WR": null, "# GD": 1, "GD WR": null, "# GIH": 2, "GIH WR": null, "IWD": null, "ALSA": 2.447004608294931, "name": "Cryptcaller Chariot", "color": "B", "rarity": "rare"}, "Cursecloth Wrappings": {"# OH": 4, "OH WR": null, "# GD": 9, "GD WR": null, "# GIH": 13, "GIH WR": null, "IWD": null, "ALSA": 2.319182389937107, "name": "Cursecloth Wrappings", "color": "B", "rarity": "rare"}, "Deathless Pilot": {"# OH": 0, "OH WR": null, "# GD": 0, "GD WR": null, "# GIH": 0, "GIH WR": null, "IWD": null, "ALSA": 5.942695851307451, "name": "Deathless Pilot", "color": "B", "rarity": "common"}, "Demonic Junker": {"# OH": 23, "OH WR": null, "# GD": 28, "GD WR": null, "# GIH": 51, "GIH WR": null, "IWD": null, "ALSA": 1.8882466281310213, "name": "Demonic Junker", "color": "B", "rarity": "rare"}, "Engine Rat": {"# OH": 0, "OH WR": null, "# GD": 0, "GD WR": null, "# GIH": 0, "GIH WR": null, "IWD": null, "ALSA": 5.425141884222475, "name": "Engine Rat", "color": "B", "rarity": "common"}, "Gas Guzzler": {"# OH": 0, "OH WR": null, "# GD": 0, "GD WR": null, "# GIH": 0, "GIH WR": null, "IWD": null, "ALSA": 2.5762483130904186, "name": "Gas Guzzler", "color": "B", "rarity": "rare"}, "Gastal Raider": {"# OH": 0, "OH WR": null, "# GD": 0, "GD WR": null, "# GIH": 0, "GIH WR": null, "IWD": null, "ALSA": 4.025950292397661, "name": "Gastal Raider", "color": "B", "rarity": "uncommon"}, "Gonti, Night Minister": {"# OH": 4, "OH WR": null, "# GD": 12, "GD WR": null, "# GIH": 16, "GIH WR": null, "IWD": null, "ALSA": 1.810492505353319, "name": "Gonti, Night Minister", "color": "B", "rarity": "rare"}, "Grim Bauble": {"# OH": 5, "OH WR": null, "# GD": 7, "GD WR": null, "# GIH": 12, "GIH WR": null, "IWD": null, "ALSA": 3.932833605462372, "name": "Grim Bauble", "color": "B", "rarity": "common"}, "Grim Javelineer": {"# OH": 0, "OH WR": null, "# GD": 0, "GD WR": null, "# GIH": 0, "GIH WR": null, "IWD": null, "ALSA": 6.858962874489897, "name": "Grim Javelineer", "color": "B", "rarity": "common"}, "Hellish Sideswipe": {"# OH": 1, "OH WR": null, "# GD": 1, "GD WR": null, "# GIH": 2, "GIH WR": null, "IWD": null, "ALSA": 4.3710513120508105, "name": "Hellish Sideswipe", "color": "B", "rarity": "uncommon"}, "Hour of Victory": {"# OH": 4, "OH WR": null, "# GD": 7, "GD WR": null, "# GIH": 11, "GIH WR": null, "IWD": null, "ALSA": 4.64396980889674, "name": "Hour of Victory", "color": "B", "rarity": "uncommon"}, "Intimidation Tactics": {"# OH": 0, "OH WR": null, "# GD": 0, "GD WR": null, "# GIH": 0, "GIH WR": null, "IWD": null, "ALSA": 5.425358448130447, "name": "Intimidation Tactics", "color": "B", "rarity": "uncommon"}, "Kalakscion, Hunger Tyrant": {"# OH": 0, "OH WR": null, "# GD": 0, "GD WR": null, "# GIH": 0, "GIH WR": null, "IWD": null, "ALSA": 6.183962872244424, "name": "Kalakscion, Hunger Tyrant", "color": "B", "rarity": "uncommon"}, "The Last Ride": {"# OH": 0, "OH WR": null, "# GD": 0, "GD WR": null, "# GIH": 0, "GIH WR": null, "IWD": null, "ALSA": 2.6288951841359776, "name": "The Last Ride", "color": "B", "rarity": "mythic"}, "Locust Spray": {"# OH": 0, "OH WR": null, "# GD": 0, "GD WR": null, "# GIH": 0, "GIH WR": null, "IWD": null, "ALSA": 5.820247670113622, "name": "Locust Spray", "color": "B", "rarity": "uncommon"}, "Maximum Overdrive": {"# OH": 4, "OH WR": null, "# GD": 6, "GD WR": null, "# GIH": 10, "GIH WR": null, "IWD": null, "ALSA": 6.350404868740007, "name": "Maximum Overdrive", "color": "B", "rarity": "common"}, "Momentum Breaker": {"# OH": 10, "OH WR": null, "# GD": 8, "GD WR": null, "# GIH": 18, "GIH WR": null, "IWD": null, "ALSA": 3.6241610738255035, "name": "Momentum Breaker", "color": "B", "rarity": "uncommon"}, "Mutant Surveyor": {"# OH": 0, "OH WR": null, "# GD": 0, "GD WR": null, "# GIH": 0, "GIH WR": null, "IWD": null, "ALSA": 6.313460951023317, "name": "Mutant Surveyor", "color": "B", "rarity": "common"}, "Pactdoll Terror": {"# OH": 12, "OH WR": null, "# GD": 18, "GD WR": null, "# GIH": 30, "GIH WR": null, "IWD": null, "ALSA": 4.472237196765499, "name": "Pactdoll Terror", "color": "B", "rarity": "common"}, "Quag Feast": {"# OH": 10, "OH WR": null, "# GD": 20, "GD WR": null, "# GIH": 30, "GIH WR": null, "IWD": null, "ALSA": 2.3509771986970684, "name": "Quag Feast", "color": "B", "rarity": "rare"}, "Ripclaw Wrangler": {"# OH": 1, "OH WR": null, "# GD": 2, "GD WR": null, "# GIH": 3, "GIH WR": null, "IWD": null, "ALSA": 7.171031096563011, "name": "Ripclaw Wrangler", "color": "B", "rarity": "common"}, "Risen Necroregent": {"# OH": 6, "OH WR": null, "# GD": 10, "GD WR": null, "# GIH": 16, "GIH WR": null, "IWD": null, "ALSA": 3.5214514407684097, "name": "Risen Necroregent", "color": "B", "rarity": "uncommon"}, "Risky Shortcut": {"# OH": 0, "OH WR": null, "# GD": 0, "GD WR": null, "# GIH": 0, "GIH WR": null, "IWD": null, "ALSA": 6.909196154426939, "name": "Risky Shortcut", "color": "B", "rarity": "common"}, "Shefet Archfiend": {"# OH": 1, "OH WR": null, "# GD": 3, "GD WR": null, "# GIH": 4, "GIH WR": null, "IWD": null, "ALSA": 5.143879637744669, "name": "Shefet Archfiend", "color": "B", "rarity": "uncommon"}, "The Speed Demon": {"# OH": 0, "OH WR": null, "# GD": 0, "GD WR": null, "# GIH": 0, "GIH WR": null, "IWD": null, "ALSA": null, "name": "The Speed Demon", "color": "B", "rarity": "mythic"}, "Spin Out": {"# OH": 4, "OH WR": null, "# GD": 6, "GD WR": null, "# GIH": 10, "GIH WR": null, "IWD": null, "ALSA": 3.107118038320262, "name": "Spin Out", "color": "B", "rarity": "common"}, "Streaking Oilgorger": {"# OH": 2, "OH WR": null, "# GD": 3, "GD WR": null, "# GIH": 5, "GIH WR": null, "IWD": null, "ALSA": 6.6675172237815765, "name": "Streaking Oilgorger", "color": "B", "rarity": "common"}, "Syphon Fuel": {"# OH": 21, "OH WR": null, "# GD": 19, "GD WR": null, "# GIH": 40, "GIH WR": null, "IWD": null, "ALSA": 6.007810009563277, "name": "Syphon Fuel", "color": "B", "rarity": "common"}, "Wickerfolk Indomitable": {"# OH": 0, "OH WR": null, "# GD": 0, "GD WR": null, "# GIH": 0, "GIH WR": null, "IWD": null, "ALSA": 5.797463230333288, "name": "Wickerfolk Indomitable", "color": "B", "rarity": "uncommon"}, "Wreckage Wickerfolk": {"# OH": 1, "OH WR": null, "# GD": 3, "GD WR": null, "# GIH": 4, "GIH WR": null, "IWD": null, "ALSA": 4.6156556758117295, "name": "Wreckage Wickerfolk", "color": "B", "rarity": "common"}, "Wretched Doll": {"# OH": 0, "OH WR": null, "# GD": 0, "GD WR": null, "# GIH": 0, "GIH WR": null, "IWD": null, "ALSA": 4.29067392784207, "name": "Wretched Doll", "color": "B", "rarity": "uncommon"}, "Adrenaline Jockey": {"# OH": 0, "OH WR": null, "# GD": 0, "GD WR": null, "# GIH": 0, "GIH WR": null, "IWD": null, "ALSA": 4.473229132025274, "name": "Adrenaline Jockey", "color": "R", "rarity": "uncommon"}, "Boommobile": {"# OH": 1, "OH WR": null, "# GD": 2, "GD WR": null, "# GIH": 3, "GIH WR": null, "IWD": null, "ALSA": 1.79037111334002, "name": "Boommobile", "color": "R", "rarity": "rare"}, "Burner Rocket": {"# OH": 0, "OH WR": null, "# GD": 0, "GD WR": null, "# GIH": 0, "GIH WR": null, "IWD": null, "ALSA": 6.792716808890653, "name": "Burner Rocket", "color": "R", "rarity": "common"}, "Burnout Bashtronaut": {"# OH": 2, "OH WR": null, "# GD": 4, "GD WR": null, "# GIH": 6, "GIH WR": null, "IWD": null, "ALSA": 2.0584642233856894, "name": "Burnout Bashtronaut", "color": "R", "rarity": "rare"}, "Chandra, Spark Hunter": {"# OH": 15, "OH WR": null, "# GD": 37, "GD WR": null, "# GIH": 52, "GIH WR": null, "IWD": null, "ALSA": null, "name": "Chandra, Spark Hunter", "color": "R", "rarity": "mythic"}, "Clamorous Ironclad": {"# OH": 0, "OH WR": null, "# GD": 0, "GD WR": null, "# GIH": 0, "GIH WR": null, "IWD": null, "ALSA": 6.589852116267211, "name": "Clamorous Ironclad", "color": "R", "rarity": "common"}, "Count on Luck": {"# OH": 0, "OH WR": null, "# GD": 0, "GD WR": null, "# GIH": 0, "GIH WR": null, "IWD": null, "ALSA": 4.85968660968661, "name": "Count on Luck", "color": "R", "rarity": "rare"}, "Crash and Burn": {"# OH": 30, "OH WR": null, "# GD": 36, "GD WR": null, "# GIH": 66, "GIH WR": null, "IWD": null, "ALSA": 4.696411619517752, "name": "Crash and Burn", "color": "R", "rarity": "common"}, "Daretti, Rocketeer Engineer": {"# OH": 0, "OH WR": null, "# GD": 0, "GD WR": null, "# GIH": 0, "GIH WR": null, "IWD": null, "ALSA": 3.5005170630816957, "name": "Daretti, Rocketeer Engineer", "color": "R", "rarity": "rare"}, "Draconautics Engineer": {"# OH": 36, "OH WR": null, "# GD": 59, "GD WR": null, "# GIH": 95, "GIH WR": null, "IWD": null, "ALSA": 1.5978773584905661, "name": "Draconautics Engineer", "color": "R", "rarity": "rare"}, "Dracosaur Auxiliary": {"# OH": 2, "OH WR": null, "# GD": 4, "GD WR": null, "# GIH": 6, "GIH WR": null, "IWD": null, "ALSA": 3.6132153149444215, "name": "Dracosaur Auxiliary", "color": "R", "rarity": "uncommon"}, "Dynamite Diver": {"# OH": 0, "OH WR": null, "# GD": 0, "GD WR": null, "# GIH": 0, "GIH WR": null, "IWD": null, "ALSA": 6.7625216770376415, "name": "Dynamite Diver", "color": "R", "rarity": "common"}, "Endrider Catalyzer": {"# OH": 0, "OH WR": null, "# GD": 0, "GD WR": null, "# GIH": 0, "GIH WR": null, "IWD": null, "ALSA": 5.958362434857357, "name": "Endrider Catalyzer", "color": "R", "rarity": "common"}, "Endrider Spikespitter": {"# OH": 4, "OH WR": null, "# GD": 10, "GD WR": null, "# GIH": 14, "GIH WR": null, "IWD": null, "ALSA": 3.7026812313803377, "name": "Endrider Spikespitter", "color": "R", "rarity": "uncommon"}, "Fuel the Flames": {"# OH": 4, "OH WR": null, "# GD": 5, "GD WR": null, "# GIH": 9, "GIH WR": null, "IWD": null, "ALSA": 5.880616682039794, "name": "Fuel the Flames", "color": "R", "rarity": "uncommon"}, "Full Throttle": {"# OH": 0, "OH WR": null, "# GD": 0, "GD WR": null, "# GIH": 0, "GIH WR": null, "IWD": null, "ALSA": 5.027472527472527, "name": "Full Throttle", "color": "R", "rarity": "rare"}, "Gastal Blockbuster": {"# OH": 0, "OH WR": null, "# GD": 0, "GD WR": null, "# GIH": 0, "GIH WR": null, "IWD": null, "ALSA": 7.093561516206542, "name": "Gastal Blockbuster", "color": "R", "rarity": "common"}, "Gastal Thrillroller": {"# OH": 13, "OH WR": null, "# GD": 14, "GD WR": null, "# GIH": 27, "GIH WR": null, "IWD": null, "ALSA": 2.19327731092437, "name": "Gastal Thrillroller", "color": "R", "rarity": "rare"}, "Gilded Ghoda": {"# OH": 0, "OH WR": null, "# GD": 1, "GD WR": null, "# GIH": 1, "GIH WR": null, "IWD": null, "ALSA": 5.72833279097516, "name": "Gilded Ghoda", "color": "R", "rarity": "common"}, "Goblin Surveyor": {"# OH": 0, "OH WR": null, "# GD": 0, "GD WR": null, "# GIH": 0, "GIH WR": null, "IWD": null, "ALSA": 6.807147504880124, "name": "Goblin Surveyor", "color": "R", "rarity": "common"}, "Greasewrench Goblin": {"# OH": 1, "OH WR": null, "# GD": 0, "GD WR": null, "# GIH": 1, "GIH WR": null, "IWD": null, "ALSA": 3.777458309373203, "name": "Greasewrench Goblin", "color": "R", "rarity": "uncommon"}, "Hazoret, Godseeker": {"# OH": 8, "OH WR": null, "# GD": 9, "GD WR": null, "# GIH": 17, "GIH WR": null, "IWD": null, "ALSA": null, "name": "Hazoret, Godseeker", "color": "R", "rarity": "mythic"}, "Howlsquad Heavy": {"# OH": 15, "OH WR": null, "# GD": 32, "GD WR": null, "# GIH": 47, "GIH WR": null, "IWD": null, "ALSA": 1.7534685165421557, "name": "Howlsquad Heavy", "color": "R", "rarity": "rare"}, "Kickoff Celebrations": {"# OH": 4, "OH WR": null, "# GD": 0, "GD WR": null, "# GIH": 4, "GIH WR": null, "IWD": null, "ALSA": 6.8944768303527315, "name": "Kickoff Celebrations", "color": "R", "rarity": "common"}, "Lightning Strike": {"# OH": 39, "OH WR": null, "# GD": 38, "GD WR": null, "# GIH": 77, "GIH WR": null, "IWD": null, "ALSA": 3.201333580292647, "name": "Lightning Strike", "color": "R", "rarity": "common"}, "Magmakin Artillerist": {"# OH": 0, "OH WR": null, "# GD": 0, "GD WR": null, "# GIH": 0, "GIH WR": null, "IWD": null, "ALSA": 6.738526663569253, "name": "Magmakin Artillerist", "color": "R", "rarity": "common"}, "Marauding Mako": {"# OH": 1, "OH WR": null, "# GD": 3, "GD WR": null, "# GIH": 4, "GIH WR": null, "IWD": null, "ALSA": 4.50667342456496, "name": "Marauding Mako", "color": "R", "rarity": "uncommon"}, "Outpace Oblivion": {"# OH": 24, "OH WR": null, "# GD": 30, "GD WR": null, "# GIH": 54, "GIH WR": null, "IWD": null, "ALSA": 2.8314462171899124, "name": "Outpace Oblivion", "color": "R", "rarity": "uncommon"}, "Pacesetter Paragon": {"# OH": 3, "OH WR": null, "# GD": 2, "GD WR": null, "# GIH": 5, "GIH WR": null, "IWD": null, "ALSA": 4.744186046511628, "name": "Pacesetter Paragon", "color": "R", "rarity": "uncommon"}, "Pedal to the Metal": {"# OH": 0, "OH WR": null, "# GD": 0, "GD WR": null, "# GIH": 0, "GIH WR": null, "IWD": null, "ALSA": 7.702872187649593, "name": "Pedal to the Metal", "color": "R", "rarity": "common"}, "Prowcatcher Specialist": {"# OH": 0, "OH WR": null, "# GD": 0, "GD WR": null, "# GIH": 0, "GIH WR": null, "IWD": null, "ALSA": 5.922039795585517, "name": "Prowcatcher Specialist", "color": "R", "rarity": "common"}, "Push the Limit": {"# OH": 0, "OH WR": null, "# GD": 0, "GD WR": null, "# GIH": 0, "GIH WR": null, "IWD": null, "ALSA": 7.140444015444015, "name": "Push the Limit", "color": "R", "rarity": "uncommon"}, "Reckless Velocitaur": {"# OH": 0, "OH WR": null, "# GD": 0, "GD WR": null, "# GIH": 0, "GIH WR": null, "IWD": null, "ALSA": 5.806380638063806, "name": "Reckless Velocitaur", "color": "R", "rarity": "uncommon"}, "Road Rage": {"# OH": 8, "OH WR": null, "# GD": 20, "GD WR": null, "# GIH": 28, "GIH WR": null, "IWD": null, "ALSA": 3.269475532148343, "name": "Road Rage", "color": "R", "rarity": "uncommon"}, "Skycrash": {"# OH": 5, "OH WR": null, "# GD": 2, "GD WR": null, "# GIH": 7, "GIH WR": null, "IWD": null, "ALSA": 4.260243819844226, "name": "Skycrash", "color": "R", "rarity": "uncommon"}, "Spire Mechcycle": {"# OH": 1, "OH WR": null, "# GD": 5, "GD WR": null, "# GIH": 6, "GIH WR": null, "IWD": null, "ALSA": 4.3526999316473, "name": "Spire Mechcycle", "color": "R", "rarity": "uncommon"}, "Thunderhead Gunner": {"# OH": 75, "OH WR": null, "# GD": 136, "GD WR": null, "# GIH": 211, "GIH WR": null, "IWD": null, "ALSA": 5.614013859861402, "name": "Thunderhead Gunner", "color": "R", "rarity": "common"}, "Tyrox, Saurid Tyrant": {"# OH": 3, "OH WR": null, "# GD": 3, "GD WR": null, "# GIH": 6, "GIH WR": null, "IWD": null, "ALSA": 5.720274083031036, "name": "Tyrox, Saurid Tyrant", "color": "R", "rarity": "uncommon"}, "Afterburner Expert": {"# OH": 236, "OH WR": null, "# GD": 296, "GD WR": null, "# GIH": 532, "GIH WR": 0.6785714285714286, "IWD": 0.10693400167084377, "ALSA": 1.6923076923076923, "name": "Afterburner Expert", "color": "G", "rarity": "rare"}, "Agonasaur Rex": {"# OH": 199, "OH WR": null, "# GD": 324, "GD WR": null, "# GIH": 523, "GIH WR": 0.7074569789674953, "IWD": 0.13189427800286502, "ALSA": 1.5482673267326732, "name": "Agonasaur Rex", "color": "G", "rarity": "rare"}, "Alacrian Jaguar": {"# OH": 120, "OH WR": null, "# GD": 170, "GD WR": null, "# GIH": 290, "GIH WR": null, "IWD": null, "ALSA": 7.033338265029344, "name": "Alacrian Jaguar", "color": "G", "rarity": "common"}, "Autarch Mammoth": {"# OH": 537, "OH WR": 0.6238361266294227, "# GD": 852, "GD WR": 0.6514084507042254, "# GIH": 1389, "GIH WR": 0.640748740100792, "IWD": 0.03202814342838811, "ALSA": 2.7771925204108507, "name": "Autarch Mammoth", "color": "G", "rarity": "uncommon"}, "Beastrider Vanguard": {"# OH": 1085, "OH WR": 0.6101382488479262, "# GD": 1640, "GD WR": 0.6115853658536585, "# GIH": 2725, "GIH WR": 0.6110091743119266, "IWD": 0.004122946767016411, "ALSA": 5.202021952628538, "name": "Beastrider Vanguard", "color": "G", "rarity": "common"}, "Bestow Greatness": {"# OH": 293, "OH WR": null, "# GD": 495, "GD WR": null, "# GIH": 788, "GIH WR": 0.6104060913705583, "IWD": -0.004903986148821482, "ALSA": 7.307322004525105, "name": "Bestow Greatness", "color": "G", "rarity": "common"}, "Broken Wings": {"# OH": 694, "OH WR": 0.5504322766570605, "# GD": 1040, "GD WR": 0.6423076923076924, "# GIH": 1734, "GIH WR": 0.6055363321799307, "IWD": 0.0018999685435671099, "ALSA": 5.978759289516682, "name": "Broken Wings", "color": "G", "rarity": "common"}, "Defend the Rider": {"# OH": 367, "OH WR": null, "# GD": 566, "GD WR": 0.6148409893992933, "# GIH": 933, "GIH WR": 0.6291532690246516, "IWD": 0.02041886617260169, "ALSA": 4.229468599033816, "name": "Defend the Rider", "color": "G", "rarity": "uncommon"}, "District Mascot": {"# OH": 136, "OH WR": null, "# GD": 204, "GD WR": null, "# GIH": 340, "GIH WR": null, "IWD": null, "ALSA": 2.077054794520548, "name": "District Mascot", "color": "G", "rarity": "rare"}, "Dredger's Insight": {"# OH": 236, "OH WR": null, "# GD": 349, "GD WR": null, "# GIH": 585, "GIH WR": 0.6239316239316239, "IWD": 0.02559367379311983, "ALSA": 5.33645390070922, "name": "Dredger's Insight", "color": "G", "rarity": "uncommon"}, "Earthrumbler": {"# OH": 388, "OH WR": null, "# GD": 555, "GD WR": 0.6486486486486487, "# GIH": 943, "GIH WR": 0.6246023329798516, "IWD": 0.04947279930109505, "ALSA": 3.4646180480415496, "name": "Earthrumbler", "color": "G", "rarity": "uncommon"}, "Elvish Refueler": {"# OH": 582, "OH WR": 0.6305841924398625, "# GD": 829, "GD WR": 0.6501809408926418, "# GIH": 1411, "GIH WR": 0.6420978029766123, "IWD": 0.040839221740914367, "ALSA": 2.9435084241823586, "name": "Elvish Refueler", "color": "G", "rarity": "uncommon"}, "Fang Guardian": {"# OH": 503, "OH WR": 0.6222664015904572, "# GD": 712, "GD WR": 0.6390449438202247, "# GIH": 1215, "GIH WR": 0.6320987654320988, "IWD": 0.03236123262369983, "ALSA": 3.877470355731225, "name": "Fang Guardian", "color": "G", "rarity": "uncommon"}, "Fang-Druid Summoner": {"# OH": 418, "OH WR": null, "# GD": 596, "GD WR": 0.5956375838926175, "# GIH": 1014, "GIH WR": 0.5996055226824457, "IWD": 7.574211818239807e-05, "ALSA": 4.339638433210579, "name": "Fang-Druid Summoner", "color": "G", "rarity": "uncommon"}, "Greenbelt Guardian": {"# OH": 569, "OH WR": 0.6397188049209139, "# GD": 785, "GD WR": 0.6420382165605095, "# GIH": 1354, "GIH WR": 0.6410635155096012, "IWD": 0.03883992069798903, "ALSA": 2.8707323429762837, "name": "Greenbelt Guardian", "color": "G", "rarity": "uncommon"}, "Hazard of the Dunes": {"# OH": 1324, "OH WR": 0.5944108761329305, "# GD": 2048, "GD WR": 0.62939453125, "# GIH": 3372, "GIH WR": 0.6156583629893239, "IWD": -0.001974828901293746, "ALSA": 3.7531790537872207, "name": "Hazard of the Dunes", "color": "G", "rarity": "common"}, "Jibbirik Omnivore": {"# OH": 908, "OH WR": 0.6090308370044053, "# GD": 1225, "GD WR": 0.5828571428571429, "# GIH": 2133, "GIH WR": 0.5939990623534928, "IWD": -0.003930873952239677, "ALSA": 5.662665198237885, "name": "Jibbirik Omnivore", "color": "G", "rarity": "common"}, "Loxodon Surveyor": {"# OH": 376, "OH WR": null, "# GD": 608, "GD WR": 0.5805921052631579, "# GIH": 984, "GIH WR": 0.5863821138211383, "IWD": -0.014283443583187894, "ALSA": 5.953976189249085, "name": "Loxodon Surveyor", "color": "G", "rarity": "common"}, "Lumbering Worldwagon": {"# OH": 192, "OH WR": null, "# GD": 256, "GD WR": null, "# GIH": 448, "GIH WR": null, "IWD": null, "ALSA": 1.585812356979405, "name": "Lumbering Worldwagon", "color": "G", "rarity": "rare"}, "March of the World Ooze": {"# OH": 89, "OH WR": null, "# GD": 110, "GD WR": null, "# GIH": 199, "GIH WR": null, "IWD": null, "ALSA": null, "name": "March of the World Ooze", "color": "G", "rarity": "mythic"}, "Migrating Ketradon": {"# OH": 1421, "OH WR": 0.6059113300492611, "# GD": 2258, "GD WR": 0.6364038972542073, "# GIH": 3679, "GIH WR": 0.624626257135091, "IWD": 0.018220410187541614, "ALSA": 4.495362028695362, "name": "Migrating Ketradon", "color": "G", "rarity": "common"}, "Molt Tender": {"# OH": 515, "OH WR": 0.6504854368932039, "# GD": 720, "GD WR": 0.6277777777777778, "# GIH": 1235, "GIH WR": 0.637246963562753, "IWD": 0.019153460223348073, "ALSA": 4.179652173913044, "name": "Molt Tender", "color": "G", "rarity": "uncommon"}, "Ooze Patrol": {"# OH": 66, "OH WR": null, "# GD": 125, "GD WR": null, "# GIH": 191, "GIH WR": null, "IWD": null, "ALSA": 5.064917541229385, "name": "Ooze Patrol", "color": "G", "rarity": "uncommon"}, "Oviya, Automech Artisan": {"# OH": 31, "OH WR": null, "# GD": 54, "GD WR": null, "# GIH": 85, "GIH WR": null, "IWD": null, "ALSA": 3.06763590391909, "name": "Oviya, Automech Artisan", "color": "G", "rarity": "rare"}, "Plow Through": {"# OH": 369, "OH WR": null, "# GD": 636, "GD WR": 0.6069182389937107, "# GIH": 1005, "GIH WR": 0.609950248756219, "IWD": 0.003567270032814651, "ALSA": 3.2507909723686987, "name": "Plow Through", "color": "G", "rarity": "uncommon"}, "Point the Way": {"# OH": 16, "OH WR": null, "# GD": 22, "GD WR": null, "# GIH": 38, "GIH WR": null, "IWD": null, "ALSA": 6.872819497711246, "name": "Point the Way", "color": "G", "rarity": "uncommon"}, "Pothole Mole": {"# OH": 1108, "OH WR": 0.5974729241877257, "# GD": 1648, "GD WR": 0.595873786407767, "# GIH": 2756, "GIH WR": 0.5965166908563135, "IWD": -0.0092391068525437, "ALSA": 4.980677782459519, "name": "Pothole Mole", "color": "G", "rarity": "common"}, "Regal Imperiosaur": {"# OH": 143, "OH WR": null, "# GD": 221, "GD WR": null, "# GIH": 364, "GIH WR": null, "IWD": null, "ALSA": 2.0913081650570677, "name": "Regal Imperiosaur", "color": "G", "rarity": "rare"}, "Rise from the Wreck": {"# OH": 180, "OH WR": null, "# GD": 272, "GD WR": null, "# GIH": 452, "GIH WR": null, "IWD": null, "ALSA": 5.168857431749242, "name": "Rise from the Wreck", "color": "G", "rarity": "uncommon"}, "Run Over": {"# OH": 1294, "OH WR": 0.5811437403400309, "# GD": 1952, "GD WR": 0.6465163934426229, "# GIH": 3246, "GIH WR": 0.6204559457794209, "IWD": 0.022965598289073408, "ALSA": 3.3494562853414527, "name": "Run Over", "color": "G", "rarity": "common"}, "Silken Strength": {"# OH": 135, "OH WR": null, "# GD": 218, "GD WR": null, "# GIH": 353, "GIH WR": null, "IWD": null, "ALSA": 7.565074683664732, "name": "Silken Strength", "color": "G", "rarity": "common"}, "Stampeding Scurryfoot": {"# OH": 1598, "OH WR": 0.6433041301627034, "# GD": 2510, "GD WR": 0.6442231075697211, "# GIH": 4108, "GIH WR": 0.6438656280428432, "IWD": 0.026738131883088934, "ALSA": 3.9873983442010403, "name": "Stampeding Scurryfoot", "color": "G", "rarity": "common"}, "Terrian, World Tyrant": {"# OH": 376, "OH WR": null, "# GD": 551, "GD WR": 0.6152450090744102, "# GIH": 927, "GIH WR": 0.6051779935275081, "IWD": -0.0013479181807452, "ALSA": 3.888230798624379, "name": "Terrian, World Tyrant", "color": "G", "rarity": "uncommon"}, "Thunderous Velocipede": {"# OH": 73, "OH WR": null, "# GD": 114, "GD WR": null, "# GIH": 187, "GIH WR": null, "IWD": null, "ALSA": null, "name": "Thunderous Velocipede", "color": "G", "rarity": "mythic"}, "Veloheart Bike": {"# OH": 560, "OH WR": 0.6339285714285714, "# GD": 865, "GD WR": 0.5965317919075145, "# GIH": 1425, "GIH WR": 0.6112280701754386, "IWD": 0.012867414437733649, "ALSA": 5.35391617035622, "name": "Veloheart Bike", "color": "G", "rarity": "common"}, "Venomsac Lagac": {"# OH": 943, "OH WR": 0.6097560975609756, "# GD": 1473, "GD WR": 0.6001357773251867, "# GIH": 2416, "GIH WR": 0.6038907284768212, "IWD": -0.013766091967918226, "ALSA": 4.568472844256608, "name": "Venomsac Lagac", "color": "G", "rarity": "common"}, "Webstrike Elite": {"# OH": 218, "OH WR": null, "# GD": 290, "GD WR": null, "# GIH": 508, "GIH WR": 0.639763779527559, "IWD": 0.024621823691596934, "ALSA": 2.1555733761026463, "name": "Webstrike Elite", "color": "G", "rarity": "rare"}, "Aatchik, Emerald Radian": {"# OH": 5, "OH WR": null, "# GD": 9, "GD WR": null, "# GIH": 14, "GIH WR": null, "IWD": null, "ALSA": 2.4963289280469896, "name": "Aatchik, Emerald Radian", "color": "BG", "rarity": "rare"}, "Apocalypse Runner": {"# OH": 0, "OH WR": null, "# GD": 0, "GD WR": null, "# GIH": 0, "GIH WR": null, "IWD": null, "ALSA": 5.880038921323325, "name": "Apocalypse Runner", "color": "BR", "rarity": "uncommon"}, "Boom Scholar": {"# OH": 56, "OH WR": null, "# GD": 79, "GD WR": null, "# GIH": 135, "GIH WR": null, "IWD": null, "ALSA": 4.450959860383944, "name": "Boom Scholar", "color": "RG", "rarity": "uncommon"}, "Boosted Sloop": {"# OH": 9, "OH WR": null, "# GD": 15, "GD WR": null, "# GIH": 24, "GIH WR": null, "IWD": null, "ALSA": 5.061609907120743, "name": "Boosted Sloop", "color": "UR", "rarity": "uncommon"}, "Brightglass Gearhulk": {"# OH": 0, "OH WR": null, "# GD": 0, "GD WR": null, "# GIH": 0, "GIH WR": null, "IWD": null, "ALSA": 2.360790774299835, "name": "Brightglass Gearhulk", "color": "WG", "rarity": "mythic"}, "Broadside Barrage": {"# OH": 134, "OH WR": null, "# GD": 191, "GD WR": null, "# GIH": 325, "GIH WR": null, "IWD": null, "ALSA": 4.254503708936771, "name": "Broadside Barrage", "color": "UR", "rarity": "uncommon"}, "Broodheart Engine": {"# OH": 19, "OH WR": null, "# GD": 42, "GD WR": null, "# GIH": 61, "GIH WR": null, "IWD": null, "ALSA": 4.415734391916276, "name": "Broodheart Engine", "color": "BG", "rarity": "uncommon"}, "Captain Howler, Sea Scourge": {"# OH": 13, "OH WR": null, "# GD": 30, "GD WR": null, "# GIH": 43, "GIH WR": null, "IWD": null, "ALSA": 2.850515463917526, "name": "Captain Howler, Sea Scourge", "color": "UR", "rarity": "rare"}, "Caradora, Heart of Alacria": {"# OH": 32, "OH WR": null, "# GD": 38, "GD WR": null, "# GIH": 70, "GIH WR": null, "IWD": null, "ALSA": 2.8500331785003317, "name": "Caradora, Heart of Alacria", "color": "WG", "rarity": "rare"}, "Cloudspire Coordinator": {"# OH": 0, "OH WR": null, "# GD": 0, "GD WR": null, "# GIH": 0, "GIH WR": null, "IWD": null, "ALSA": 5.073600776447751, "name": "Cloudspire Coordinator", "color": "WR", "rarity": "uncommon"}, "Cloudspire Skycycle": {"# OH": 0, "OH WR": null, "# GD": 0, "GD WR": null, "# GIH": 0, "GIH WR": null, "IWD": null, "ALSA": 5.027536002532046, "name": "Cloudspire Skycycle", "color": "WR", "rarity": "uncommon"}, "Coalstoke Gearhulk": {"# OH": 0, "OH WR": null, "# GD": 0, "GD WR": null, "# GIH": 0, "GIH WR": null, "IWD": null, "ALSA": 2.375558867362146, "name": "Coalstoke Gearhulk", "color": "BR", "rarity": "mythic"}, "Debris Beetle": {"# OH": 60, "OH WR": null, "# GD": 121, "GD WR": null, "# GIH": 181, "GIH WR": null, "IWD": null, "ALSA": 2.3275145469659186, "name": "Debris Beetle", "color": "BG", "rarity": "rare"}, "Dune Drifter": {"# OH": 0, "OH WR": null, "# GD": 0, "GD WR": null, "# GIH": 0, "GIH WR": null, "IWD": null, "ALSA": 5.145715138847417, "name": "Dune Drifter", "color": "WB", "rarity": "uncommon"}, "Embalmed Ascendant": {"# OH": 0, "OH WR": null, "# GD": 0, "GD WR": null, "# GIH": 0, "GIH WR": null, "IWD": null, "ALSA": 4.753390256152687, "name": "Embalmed Ascendant", "color": "WB", "rarity": "uncommon"}, "Explosive Getaway": {"# OH": 3, "OH WR": null, "# GD": 4, "GD WR": null, "# GIH": 7, "GIH WR": null, "IWD": null, "ALSA": 3.1504322766570607, "name": "Explosive Getaway", "color": "WR", "rarity": "rare"}, "Far Fortune, End Boss": {"# OH": 0, "OH WR": null, "# GD": 3, "GD WR": null, "# GIH": 3, "GIH WR": null, "IWD": null, "ALSA": 2.489549839228296, "name": "Far Fortune, End Boss", "color": "BR", "rarity": "rare"}, "Fearless Swashbuckler": {"# OH": 9, "OH WR": null, "# GD": 8, "GD WR": null, "# GIH": 17, "GIH WR": null, "IWD": null, "ALSA": 3.4207679826933477, "name": "Fearless Swashbuckler", "color": "UR", "rarity": "rare"}, "Gastal Thrillseeker": {"# OH": 0, "OH WR": null, "# GD": 0, "GD WR": null, "# GIH": 0, "GIH WR": null, "IWD": null, "ALSA": 4.728384429900103, "name": "Gastal Thrillseeker", "color": "BR", "rarity": "uncommon"}, "Guidelight Pathmaker": {"# OH": 33, "OH WR": null, "# GD": 51, "GD WR": null, "# GIH": 84, "GIH WR": null, "IWD": null, "ALSA": 4.922321154436598, "name": "Guidelight Pathmaker", "color": "WU", "rarity": "uncommon"}, "Haunt the Network": {"# OH": 50, "OH WR": null, "# GD": 71, "GD WR": null, "# GIH": 121, "GIH WR": null, "IWD": null, "ALSA": 3.984235110938108, "name": "Haunt the Network", "color": "UB", "rarity": "uncommon"}, "Haunted Hellride": {"# OH": 0, "OH WR": null, "# GD": 1, "GD WR": null, "# GIH": 1, "GIH WR": null, "IWD": null, "ALSA": 5.403753819292885, "name": "Haunted Hellride", "color": "UB", "rarity": "uncommon"}, "Ketramose, the New Dawn": {"# OH": 0, "OH WR": null, "# GD": 0, "GD WR": null, "# GIH": 0, "GIH WR": null, "IWD": null, "ALSA": 3.5399393326592516, "name": "Ketramose, the New Dawn", "color": "WB", "rarity": "mythic"}, "Kolodin, Triumph Caster": {"# OH": 0, "OH WR": null, "# GD": 0, "GD WR": null, "# GIH": 0, "GIH WR": null, "IWD": null, "ALSA": 3.2473928157589804, "name": "Kolodin, Triumph Caster", "color": "WR", "rarity": "rare"}, "Lagorin, Soul of Alacria": {"# OH": 2, "OH WR": null, "# GD": 2, "GD WR": null, "# GIH": 4, "GIH WR": null, "IWD": null, "ALSA": 4.216954295467476, "name": "Lagorin, Soul of Alacria", "color": "WG", "rarity": "uncommon"}, "Loot, the Pathfinder": {"# OH": 112, "OH WR": null, "# GD": 196, "GD WR": null, "# GIH": 308, "GIH WR": null, "IWD": null, "ALSA": 1.9722222222222223, "name": "Loot, the Pathfinder", "color": "URG", "rarity": "mythic"}, "Mendicant Core, Guidelight": {"# OH": 6, "OH WR": null, "# GD": 8, "GD WR": null, "# GIH": 14, "GIH WR": null, "IWD": null, "ALSA": 2.8172733761598856, "name": "Mendicant Core, Guidelight", "color": "WU", "rarity": "rare"}, "Mimeoplasm, Revered One": {"# OH": 30, "OH WR": null, "# GD": 39, "GD WR": null, "# GIH": 69, "GIH WR": null, "IWD": null, "ALSA": 3.485655737704918, "name": "Mimeoplasm, Revered One", "color": "UBG", "rarity": "mythic"}, "Oildeep Gearhulk": {"# OH": 2, "OH WR": null, "# GD": 2, "GD WR": null, "# GIH": 4, "GIH WR": null, "IWD": null, "ALSA": 2.3710801393728222, "name": "Oildeep Gearhulk", "color": "UB", "rarity": "mythic"}, "Pyrewood Gearhulk": {"# OH": 10, "OH WR": null, "# GD": 16, "GD WR": null, "# GIH": 26, "GIH WR": null, "IWD": null, "ALSA": 2.137735849056604, "name": "Pyrewood Gearhulk", "color": "RG", "rarity": "mythic"}, "Rangers' Aetherhive": {"# OH": 902, "OH WR": 0.6175166297117517, "# GD": 1430, "GD WR": 0.6153846153846154, "# GIH": 2332, "GIH WR": 0.6162092624356775, "IWD": 0.0161408395824445, "ALSA": 4.374278499278499, "name": "Rangers' Aetherhive", "color": "UG", "rarity": "uncommon"}, "Redshift, Rocketeer Chief": {"# OH": 4, "OH WR": null, "# GD": 10, "GD WR": null, "# GIH": 14, "GIH WR": null, "IWD": null, "ALSA": 3.5599369085173502, "name": "Redshift, Rocketeer Chief", "color": "RG", "rarity": "rare"}, "Riptide Gearhulk": {"# OH": 7, "OH WR": null, "# GD": 14, "GD WR": null, "# GIH": 21, "GIH WR": null, "IWD": null, "ALSA": 2.1860068259385668, "name": "Riptide Gearhulk", "color": "WU", "rarity": "mythic"}, "Rocketeer Boostbuggy": {"# OH": 25, "OH WR": null, "# GD": 27, "GD WR": null, "# GIH": 52, "GIH WR": null, "IWD": null, "ALSA": 4.3584031366957765, "name": "Rocketeer Boostbuggy", "color": "RG", "rarity": "uncommon"}, "Sab-Sunen, Luxa Embodied": {"# OH": 117, "OH WR": null, "# GD": 251, "GD WR": null, "# GIH": 368, "GIH WR": null, "IWD": null, "ALSA": null, "name": "Sab-Sunen, Luxa Embodied", "color": "UG", "rarity": "mythic"}, "Samut, the Driving Force": {"# OH": 5, "OH WR": null, "# GD": 13, "GD WR": null, "# GIH": 18, "GIH WR": null, "IWD": null, "ALSA": 3.317198177676538, "name": "Samut, the Driving Force", "color": "WRG", "rarity": "rare"}, "Sita Varma, Masked Racer": {"# OH": 419, "OH WR": null, "# GD": 643, "GD WR": 0.6578538102643857, "# GIH": 1062, "GIH WR": 0.6685499058380414, "IWD": 0.08118931104250238, "ALSA": 2.84421768707483, "name": "Sita Varma, Masked Racer", "color": "UG", "rarity": "rare"}, "Skyserpent Seeker": {"# OH": 1169, "OH WR": 0.6561163387510693, "# GD": 1788, "GD WR": 0.6387024608501118, "# GIH": 2957, "GIH WR": 0.6455867433209334, "IWD": 0.04624176515499445, "ALSA": 3.797107271996786, "name": "Skyserpent Seeker", "color": "UG", "rarity": "uncommon"}, "Thundering Broodwagon": {"# OH": 51, "OH WR": null, "# GD": 55, "GD WR": null, "# GIH": 106, "GIH WR": null, "IWD": null, "ALSA": 3.7908830744071955, "name": "Thundering Broodwagon", "color": "BG", "rarity": "uncommon"}, "Veteran Beastrider": {"# OH": 49, "OH WR": null, "# GD": 80, "GD WR": null, "# GIH": 129, "GIH WR": null, "IWD": null, "ALSA": 4.003268602191886, "name": "Veteran Beastrider", "color": "WG", "rarity": "uncommon"}, "Voyage Home": {"# OH": 14, "OH WR": null, "# GD": 22, "GD WR": null, "# GIH": 36, "GIH WR": null, "IWD": null, "ALSA": 5.080976665121311, "name": "Voyage Home", "color": "WU", "rarity": "uncommon"}, "Winter, Cursed Rider": {"# OH": 1, "OH WR": null, "# GD": 2, "GD WR": null, "# GIH": 3, "GIH WR": null, "IWD": null, "ALSA": 3.3543083900226756, "name": "Winter, Cursed Rider", "color": "UB", "rarity": "rare"}, "Zahur, Glory's Past": {"# OH": 0, "OH WR": null, "# GD": 0, "GD WR": null, "# GIH": 0, "GIH WR": null, "IWD": null, "ALSA": 3.223784417106034, "name": "Zahur, Glory's Past", "color": "WB", "rarity": "rare"}, "Aetherjacket": {"# OH": 54, "OH WR": null, "# GD": 101, "GD WR": null, "# GIH": 155, "GIH WR": null, "IWD": null, "ALSA": 6.374401027515685, "name": "Aetherjacket", "color": "", "rarity": "common"}, "The Aetherspark": {"# OH": 63, "OH WR": null, "# GD": 71, "GD WR": null, "# GIH": 134, "GIH WR": null, "IWD": null, "ALSA": null, "name": "The Aetherspark", "color": "", "rarity": "mythic"}, "Camera Launcher": {"# OH": 167, "OH WR": null, "# GD": 255, "GD WR": null, "# GIH": 422, "GIH WR": null, "IWD": null, "ALSA": 6.879650939777522, "name": "Camera Launcher", "color": "", "rarity": "common"}, "Guidelight Matrix": {"# OH": 10, "OH WR": null, "# GD": 16, "GD WR": null, "# GIH": 26, "GIH WR": null, "IWD": null, "ALSA": 7.368073306004341, "name": "Guidelight Matrix", "color": "", "rarity": "common"}, "Lifecraft Engine": {"# OH": 13, "OH WR": null, "# GD": 19, "GD WR": null, "# GIH": 32, "GIH WR": null, "IWD": null, "ALSA": 2.48995148995149, "name": "Lifecraft Engine", "color": "", "rarity": "rare"}, "Marketback Walker": {"# OH": 74, "OH WR": null, "# GD": 113, "GD WR": null, "# GIH": 187, "GIH WR": null, "IWD": null, "ALSA": 1.6142684401451028, "name": "Marketback Walker", "color": "", "rarity": "rare"}, "Marshals' Pathcruiser": {"# OH": 94, "OH WR": null, "# GD": 110, "GD WR": null, "# GIH": 204, "GIH WR": null, "IWD": null, "ALSA": 6.028535512256442, "name": "Marshals' Pathcruiser", "color": "", "rarity": "uncommon"}, "Monument to Endurance": {"# OH": 6, "OH WR": null, "# GD": 11, "GD WR": null, "# GIH": 17, "GIH WR": null, "IWD": null, "ALSA": 2.799475753604194, "name": "Monument to Endurance", "color": "", "rarity": "rare"}, "Pit Automaton": {"# OH": 281, "OH WR": null, "# GD": 394, "GD WR": null, "# GIH": 675, "GIH WR": 0.5985185185185186, "IWD": 0.0021407694887644046, "ALSA": 6.121681964773009, "name": "Pit Automaton", "color": "", "rarity": "uncommon"}, "Racers' Scoreboard": {"# OH": 0, "OH WR": null, "# GD": 0, "GD WR": null, "# GIH": 0, "GIH WR": null, "IWD": null, "ALSA": 7.073272369487209, "name": "Racers' Scoreboard", "color": "", "rarity": "uncommon"}, "Radiant Lotus": {"# OH": 0, "OH WR": null, "# GD": 0, "GD WR": null, "# GIH": 0, "GIH WR": null, "IWD": null, "ALSA": 4.899240855762595, "name": "Radiant Lotus", "color": "", "rarity": "mythic"}, "Rover Blades": {"# OH": 9, "OH WR": null, "# GD": 20, "GD WR": null, "# GIH": 29, "GIH WR": null, "IWD": null, "ALSA": 5.162027699341132, "name": "Rover Blades", "color": "", "rarity": "uncommon"}, "Scrap Compactor": {"# OH": 271, "OH WR": null, "# GD": 380, "GD WR": null, "# GIH": 651, "GIH WR": 0.6067588325652842, "IWD": 0.0122285115189108, "ALSA": 6.411151339608979, "name": "Scrap Compactor", "color": "", "rarity": "common"}, "Skybox Ferry": {"# OH": 19, "OH WR": null, "# GD": 27, "GD WR": null, "# GIH": 46, "GIH WR": null, "IWD": null, "ALSA": 7.725947521865889, "name": "Skybox Ferry", "color": "", "rarity": "common"}, "Starting Column": {"# OH": 110, "OH WR": null, "# GD": 157, "GD WR": null, "# GIH": 267, "GIH WR": null, "IWD": null, "ALSA": 6.891635904410336, "name": "Starting Column", "color": "", "rarity": "common"}, "Ticket Tortoise": {"# OH": 91, "OH WR": null, "# GD": 109, "GD WR": null, "# GIH": 200, "GIH WR": null, "IWD": null, "ALSA": 7.239173884077282, "name": "Ticket Tortoise", "color": "", "rarity": "common"}, "Walking Sarcophagus": {"# OH": 33, "OH WR": null, "# GD": 45, "GD WR": null, "# GIH": 78, "GIH WR": null, "IWD": null, "ALSA": 6.937048801617095, "name": "Walking Sarcophagus", "color": "", "rarity": "common"}, "Wreck Remover": {"# OH": 64, "OH WR": null, "# GD": 100, "GD WR": null, "# GIH": 164, "GIH WR": null, "IWD": null, "ALSA": 7.723940219945484, "name": "Wreck Remover", "color": "", "rarity": "common"}, "Amonkhet Raceway": {"# OH": 6, "OH WR": null, "# GD": 2, "GD WR": null, "# GIH": 8, "GIH WR": null, "IWD": null, "ALSA": 6.987589886337276, "name": "Amonkhet Raceway", "color": "", "rarity": "uncommon"}, "Avishkar Raceway": {"# OH": 30, "OH WR": null, "# GD": 64, "GD WR": null, "# GIH": 94, "GIH WR": null, "IWD": null, "ALSA": 7.443334271507646, "name": "Avishkar Raceway", "color": "", "rarity": "common"}, "Bleachbone Verge": {"# OH": 3, "OH WR": null, "# GD": 3, "GD WR": null, "# GIH": 6, "GIH WR": null, "IWD": null, "ALSA": 4.001042028482112, "name": "Bleachbone Verge", "color": "", "rarity": "rare"}, "Bloodfell Caves": {"# OH": 9, "OH WR": null, "# GD": 31, "GD WR": null, "# GIH": 40, "GIH WR": null, "IWD": null, "ALSA": 6.836344617725371, "name": "Bloodfell Caves", "color": "", "rarity": "common"}, "Blossoming Sands": {"# OH": 83, "OH WR": null, "# GD": 113, "GD WR": null, "# GIH": 196, "GIH WR": null, "IWD": null, "ALSA": 6.582338212634823, "name": "Blossoming Sands", "color": "", "rarity": "common"}, "Country Roads": {"# OH": 0, "OH WR": null, "# GD": 1, "GD WR": null, "# GIH": 1, "GIH WR": null, "IWD": null, "ALSA": 7.113004484304933, "name": "Country Roads", "color": "", "rarity": "uncommon"}, "Dismal Backwater": {"# OH": 118, "OH WR": null, "# GD": 179, "GD WR": null, "# GIH": 297, "GIH WR": null, "IWD": null, "ALSA": 6.35911171715204, "name": "Dismal Backwater", "color": "", "rarity": "common"}, "Foul Roads": {"# OH": 4, "OH WR": null, "# GD": 7, "GD WR": null, "# GIH": 11, "GIH WR": null, "IWD": null, "ALSA": 7.308093994778068, "name": "Foul Roads", "color": "", "rarity": "uncommon"}, "Jungle Hollow": {"# OH": 135, "OH WR": null, "# GD": 175, "GD WR": null, "# GIH": 310, "GIH WR": null, "IWD": null, "ALSA": 6.195477536447486, "name": "Jungle Hollow", "color": "", "rarity": "common"}, "Muraganda Raceway": {"# OH": 2, "OH WR": null, "# GD": 10, "GD WR": null, "# GIH": 12, "GIH WR": null, "IWD": null, "ALSA": 4.610492845786964, "name": "Muraganda Raceway", "color": "", "rarity": "rare"}, "Night Market": {"# OH": 784, "OH WR": 0.610969387755102, "# GD": 1039, "GD WR": 0.5803657362848893, "# GIH": 1823, "GIH WR": 0.5935271530444323, "IWD": -0.016490736043224263, "ALSA": 4.840149132005126, "name": "Night Market", "color": "", "rarity": "common"}, "Reef Roads": {"# OH": 235, "OH WR": null, "# GD": 343, "GD WR": null, "# GIH": 578, "GIH WR": 0.5882352941176471, "IWD": -0.024432184566884008, "ALSA": 7.341474497330456, "name": "Reef Roads", "color": "", "rarity": "uncommon"}, "Riverpyre Verge": {"# OH": 29, "OH WR": null, "# GD": 53, "GD WR": null, "# GIH": 82, "GIH WR": null, "IWD": null, "ALSA": 3.9691079486289484, "name": "Riverpyre Verge", "color": "", "rarity": "rare"}, "Rocky Roads": {"# OH": 5, "OH WR": null, "# GD": 4, "GD WR": null, "# GIH": 9, "GIH WR": null, "IWD": null, "ALSA": 7.1597356727811325, "name": "Rocky Roads", "color": "", "rarity": "uncommon"}, "Rugged Highlands": {"# OH": 219, "OH WR": null, "# GD": 321, "GD WR": null, "# GIH": 540, "GIH WR": 0.6462962962962963, "IWD": 0.04344819503047348, "ALSA": 6.170919881305638, "name": "Rugged Highlands", "color": "", "rarity": "common"}, "Scoured Barrens": {"# OH": 0, "OH WR": null, "# GD": 4, "GD WR": null, "# GIH": 4, "GIH WR": null, "IWD": null, "ALSA": 6.67973917973918, "name": "Scoured Barrens", "color": "", "rarity": "common"}, "Sunbillow Verge": {"# OH": 2, "OH WR": null, "# GD": 9, "GD WR": null, "# GIH": 11, "GIH WR": null, "IWD": null, "ALSA": 4.0220994475138125, "name": "Sunbillow Verge", "color": "", "rarity": "rare"}, "Swiftwater Cliffs": {"# OH": 196, "OH WR": null, "# GD": 288, "GD WR": null, "# GIH": 484, "GIH WR": null, "IWD": null, "ALSA": 6.466775808936826, "name": "Swiftwater Cliffs", "color": "", "rarity": "common"}, "Thornwood Falls": {"# OH": 970, "OH WR": 0.6525773195876289, "# GD": 1280, "GD WR": 0.5890625, "# GIH": 2250, "GIH WR": 0.6164444444444445, "IWD": 0.0034611170233731503, "ALSA": 6.089967763993357, "name": "Thornwood Falls", "color": "", "rarity": "common"}, "Tranquil Cove": {"# OH": 121, "OH WR": null, "# GD": 156, "GD WR": null, "# GIH": 277, "GIH WR": null, "IWD": null, "ALSA": 6.696039888771694, "name": "Tranquil Cove", "color": "", "rarity": "common"}, "Wastewood Verge": {"# OH": 30, "OH WR": null, "# GD": 45, "GD WR": null, "# GIH": 75, "GIH WR": null, "IWD": null, "ALSA": 3.7285921625544267, "name": "Wastewood Verge", "color": "", "rarity": "rare"}, "Wild Roads": {"# OH": 248, "OH WR": null, "# GD": 356, "GD WR": null, "# GIH": 604, "GIH WR": 0.6125827814569537, "IWD": -0.035190497895273065, "ALSA": 6.717381174277726, "name": "Wild Roads", "color": "", "rarity": "uncommon"}, "Willowrush Verge": {"# OH": 188, "OH WR": null, "# GD": 269, "GD WR": null, "# GIH": 457, "GIH WR": null, "IWD": null, "ALSA": 3.8727469358327324, "name": "Willowrush Verge", "color": "", "rarity": "rare"}, "Wind-Scarred Crag": {"# OH": 8, "OH WR": null, "# GD": 13, "GD WR": null, "# GIH": 21, "GIH WR": null, "IWD": null, "ALSA": 6.653107991979375, "name": "Wind-Scarred Crag", "color": "", "rarity": "common"}, "Cavalier of Dawn": {"# OH": 0, "OH WR": null, "# GD": 0, "GD WR": null, "# GIH": 0, "GIH WR": null, "IWD": null, "ALSA": null, "name": "Cavalier of Dawn", "color": "W", "rarity": "mythic"}, "Thoughtcast": {"# OH": 0, "OH WR": null, "# GD": 0, "GD WR": null, "# GIH": 0, "GIH WR": null, "IWD": null, "ALSA": null, "name": "Thoughtcast", "color": "U", "rarity": "common"}, "Whir of Invention": {"# OH": 0, "OH WR": null, "# GD": 0, "GD WR": null, "# GIH": 0, "GIH WR": null, "IWD": null, "ALSA": null, "name": "Whir of Invention", "color": "U", "rarity": "rare"}, "Bone Miser": {"# OH": 0, "OH WR": null, "# GD": 0, "GD WR": null, "# GIH": 0, "GIH WR": null, "IWD": null, "ALSA": null, "name": "Bone Miser", "color": "B", "rarity": "rare"}, "Lord of the Undead": {"# OH": 0, "OH WR": null, "# GD": 0, "GD WR": null, "# GIH": 0, "GIH WR": null, "IWD": null, "ALSA": null, "name": "Lord of the Undead", "color": "B", "rarity": "rare"}, "Chandra's Ignition": {"# OH": 0, "OH WR": null, "# GD": 0, "GD WR": null, "# GIH": 0, "GIH WR": null, "IWD": null, "ALSA": null, "name": "Chandra's Ignition", "color": "R", "rarity": "rare"}, "Galvanic Blast": {"# OH": 0, "OH WR": null, "# GD": 0, "GD WR": null, "# GIH": 0, "GIH WR": null, "IWD": null, "ALSA": null, "name": "Galvanic Blast", "color": "R", "rarity": "common"}, "Pathbreaker Ibex": {"# OH": 11, "OH WR": null, "# GD": 12, "GD WR": null, "# GIH": 23, "GIH WR": null, "IWD": null, "ALSA": null, "name": "Pathbreaker Ibex", "color": "G", "rarity": "rare"}, "Chrome Mox": {"# OH": 0, "OH WR": null, "# GD": 3, "GD WR": null, "# GIH": 3, "GIH WR": null, "IWD": null, "ALSA": null, "name": "Chrome Mox", "color": "", "rarity": "mythic"}, "Skysovereign, Consul Flagship": {"# OH": 14, "OH WR": null, "# GD": 13, "GD WR": null, "# GIH": 27, "GIH WR": null, "IWD": null, "ALSA": null, "name": "Skysovereign, Consul Flagship", "color": "", "rarity": "mythic"}}